LICENSE
MANIFEST.in
README.md
setup.py
docums_select_files.egg-info/PKG-INFO
docums_select_files.egg-info/SOURCES.txt
docums_select_files.egg-info/dependency_links.txt
docums_select_files.egg-info/entry_points.txt
docums_select_files.egg-info/requires.txt
docums_select_files.egg-info/top_level.txt
selectfiles/__init__.py
selectfiles/plugin.py