Metadata-Version: 2.1
Name: docums-select-files
Version: 0.3.6
Summary: Filter pages for assignments
Home-page: https://github.com/khanhduy1407/docums-select-files
Author: NKDuy
Author-email: kn145660@gmail.com
License: Apache-2.0
Platform: UNKNOWN
